Metadata-Version: 2.2
Name: visualdsa
Version: 0.0.4
Summary: Generates visually appealing representations of data structures.
Home-page: 
Author: Sutheera Pitakpalin
Author-email: s.pitakpalin@gmail.com
License: MIT
Keywords: data structure
Classifier: Development Status :: 5 - Production/Stable
Classifier: Intended Audience :: Education
Classifier: Operating System :: Microsoft :: Windows :: Windows 10
Classifier: License :: OSI Approved :: MIT License
Classifier: Programming Language :: Python :: 3
License-File: LICENSE.txt
Requires-Dist: matplotlib
Dynamic: author
Dynamic: author-email
Dynamic: classifier
Dynamic: description
Dynamic: description-content-type
Dynamic: keywords
Dynamic: license
Dynamic: requires-dist
Dynamic: summary
